jupydebug/__init__.py
jupydebug-0.0.1.dist-info/LICENSE
jupydebug-0.0.1.dist-info/METADATA
jupydebug-0.0.1.dist-info/WHEEL
jupydebug-0.0.1.dist-info/top_level.txt
jupydebug-0.0.1.dist-info/RECORD
