Metadata-Version: 2.1
Name: jupydebug
Version: 0.0.1
Summary: a python debugger for jupyter notebooks
Home-page: https://github.com/dankluskiewicz/jupydebug
Author: Dan Kluskiewicz
Author-email: dankluskiewicz@gmail.com
License: UNKNOWN
Platform: UNKNOWN
Classifier: Programming Language :: Python :: 3
Classifier: License :: OSI Approved :: MIT License
Classifier: Operating System :: OS Independent
